awn_fpga/rtl/relu_s8.v
// relu_s8: signed int8 ReLU. Assumes symmetric quantization (zero-point = 0).
//   out[i] = (in[i] > 0) ? in[i] : 0
//
// Buffers (in_buf, out_buf) are internal regs; the testbench $readmemh's the
// input directly into hierarchical name DUT.in_buf and $writememh's out_buf.
//
// Handshake: pulse `start` for one cycle while length is valid; wait for `done`.

module relu_s8 #(
    parameter LEN = 8192,
    parameter ADDR_W = 16
)(
    input                  clk,
    input                  rst_n,
    input                  start,
    input  [ADDR_W-1:0]    length,
    output reg             done
);

reg signed [7:0] in_buf  [0:LEN-1];
reg signed [7:0] out_buf [0:LEN-1];

reg [ADDR_W:0] i;
reg busy;

integer k;
always @(posedge clk or negedge rst_n) begin
    if (!rst_n) begin
        busy <= 1'b0;
        done <= 1'b0;
        i    <= {(ADDR_W+1){1'b0}};
        for (k = 0; k < LEN; k = k + 1) out_buf[k] <= 8'sd0;
    end else begin
        done <= 1'b0;
        if (start && !busy) begin
            busy <= 1'b1;
            i    <= {(ADDR_W+1){1'b0}};
        end else if (busy) begin
            if (i < {1'b0, length}) begin
                out_buf[i[ADDR_W-1:0]] <= (in_buf[i[ADDR_W-1:0]] > 0)
                                          ? in_buf[i[ADDR_W-1:0]]
                                          : 8'sd0;
                i <= i + 1;
            end else begin
                busy <= 1'b0;
                done <= 1'b1;
            end
        end
    end
end

endmodule

awn_fpga/tb/tb_relu_s8.v
`timescale 1ns/10ps
`include "relu_s8.v"

module tb_relu_s8;

localparam CYCLE = 20;
localparam LEN = 8192;
localparam ADDR_W = 16;

reg                 clk;
reg                 rst_n;
reg                 start;
reg  [ADDR_W-1:0]   length;
wire                done;

relu_s8 #(.LEN(LEN), .ADDR_W(ADDR_W)) DUT (
    .clk(clk), .rst_n(rst_n),
    .start(start), .length(length), .done(done)
);

initial clk = 0;
always #(CYCLE/2.0) clk = ~clk;

integer arglen, code, fout, k;
reg [255:0] in_path, out_path;
reg [31:0]  cycles;

initial begin
    $dumpfile("build/wave_relu_s8.vcd");
    $dumpvars(0, tb_relu_s8);
end

initial begin
    rst_n = 1; start = 0; length = 0;

    // --- args via $value$plusargs (e.g. +len=128 +in=... +out=...)
    if (!$value$plusargs("len=%d", arglen)) arglen = 64;
    if (!$value$plusargs("in=%s",  in_path))  in_path  = "vectors/relu_in.hex";
    if (!$value$plusargs("out=%s", out_path)) out_path = "vectors/relu_out.hex";

    length = arglen[ADDR_W-1:0];

    // load input
    $readmemh(in_path, DUT.in_buf);

    // reset
    #(2*CYCLE); rst_n = 0;
    #(2*CYCLE); rst_n = 1;
    @(negedge clk);

    // start pulse
    start = 1; @(negedge clk);
    start = 0;

    // wait for done with timeout
    cycles = 0;
    while (!done) begin
        cycles = cycles + 1;
        if (cycles > 5*LEN + 1000) begin
            $display("TIMEOUT after %0d cycles", cycles);
            $finish;
        end
        @(negedge clk);
    end

    // dump output
    fout = $fopen(out_path, "w");
    if (fout == 0) begin $display("cannot open %0s", out_path); $finish; end
    for (k = 0; k < arglen; k = k + 1) begin
        $fwrite(fout, "%02x\n", DUT.out_buf[k] & 8'hff);
    end
    $fclose(fout);

    $display("relu_s8 OK len=%0d cycles=%0d", arglen, cycles);
    $finish;
end

endmodule

awn_fpga/build/wave_relu_s8.vcd
$date
	Sat May  9 19:18:57 2026
$end
$version
	Icarus Verilog
$end
$timescale
	10ps
$end
$scope module tb_relu_s8 $end
$var wire 1 ! done $end
$var reg 1 " clk $end
$var reg 32 # cycles [31:0] $end
$var reg 256 $ in_path [255:0] $end
$var reg 16 % length [15:0] $end
$var reg 256 & out_path [255:0] $end
$var reg 1 ' rst_n $end
$var reg 1 ( start $end
$var integer 32 ) arglen [31:0] $end
$var integer 32 * fout [31:0] $end
$var integer 32 + k [31:0] $end
$scope module DUT $end
$var wire 1 " clk $end
$var wire 16 , length [15:0] $end
$var wire 1 ' rst_n $end
$var wire 1 ( start $end
$var reg 1 - busy $end
$var reg 1 ! done $end
$var reg 17 . i [16:0] $end
$var integer 32 / k [31:0] $end
$upscope $end
$upscope $end
$enddefinitions $end
#0
$dumpvars
bx /
bx .
x-
b100000 ,
bx +
bx *
b100000 )
0(
1'
b111011001100101011000110111010001101111011100100111001100101111001100100011100101011111011100100110010101101100011101010101111101101111011101010111010000101110011010000110010101111000 &
b100000 %
b1110110011001010110001101110100011011110111001001110011001011110011001000111001010111110111001001100101011011000111010101011111011010010110111000101110011010000110010101111000 $
bx #
0"
x!
$end
#1000
0!
1"
#2000
0"
#3000
1"
#4000
b0 .
0-
b10000000000000 /
0"
0'
#5000
b10000000000000 /
1"
#6000
0"
#7000
b10000000000000 /
1"
#8000
1(
0"
1'
#9000
1-
1"
#10000
b1 #
0(
0"
#11000
b1 .
1"
#12000
b10 #
0"
#13000
b10 .
1"
#14000
b11 #
0"
#15000
b11 .
1"
#16000
b100 #
0"
#17000
b100 .
1"
#18000
b101 #
0"
#19000
b101 .
1"
#20000
b110 #
0"
#21000
b110 .
1"
#22000
b111 #
0"
#23000
b111 .
1"
#24000
b1000 #
0"
#25000
b1000 .
1"
#26000
b1001 #
0"
#27000
b1001 .
1"
#28000
b1010 #
0"
#29000
b1010 .
1"
#30000
b1011 #
0"
#31000
b1011 .
1"
#32000
b1100 #
0"
#33000
b1100 .
1"
#34000
b1101 #
0"
#35000
b1101 .
1"
#36000
b1110 #
0"
#37000
b1110 .
1"
#38000
b1111 #
0"
#39000
b1111 .
1"
#40000
b10000 #
0"
#41000
b10000 .
1"
#42000
b10001 #
0"
#43000
b10001 .
1"
#44000
b10010 #
0"
#45000
b10010 .
1"
#46000
b10011 #
0"
#47000
b10011 .
1"
#48000
b10100 #
0"
#49000
b10100 .
1"
#50000
b10101 #
0"
#51000
b10101 .
1"
#52000
b10110 #
0"
#53000
b10110 .
1"
#54000
b10111 #
0"
#55000
b10111 .
1"
#56000
b11000 #
0"
#57000
b11000 .
1"
#58000
b11001 #
0"
#59000
b11001 .
1"
#60000
b11010 #
0"
#61000
b11010 .
1"
#62000
b11011 #
0"
#63000
b11011 .
1"
#64000
b11100 #
0"
#65000
b11100 .
1"
#66000
b11101 #
0"
#67000
b11101 .
1"
#68000
b11110 #
0"
#69000
b11110 .
1"
#70000
b11111 #
0"
#71000
b11111 .
1"
#72000
b100000 #
0"
#73000
b100000 .
1"
#74000
b100001 #
0"
#75000
1!
0-
1"
#76000
b100000 +
b10000000000000000000000000000011 *
0"
